pyThermoDB/__init__.py
pyThermoDB/app.py
pyThermoDB/thermodb.py
pyThermoDB/thermodbX.py
pyThermoDB/api/__init__.py
pyThermoDB/api/manage.py
pyThermoDB/builder/__init__.py
pyThermoDB/builder/comp_tools.py
pyThermoDB/builder/compbuilder.py
pyThermoDB/builder/compexporter.py
pyThermoDB/config/__init__.py
pyThermoDB/config/constants.py
pyThermoDB/config/deps.py
pyThermoDB/config/main.py
pyThermoDB/config/reference.yml
pyThermoDB/config/setting.py
pyThermoDB/config/symbols.yml
pyThermoDB/core/__init__.py
pyThermoDB/core/table_util.py
pyThermoDB/core/tabledata.py
pyThermoDB/core/tableequation.py
pyThermoDB/core/tablematrixdata.py
pyThermoDB/core/tablematrixequation.py
pyThermoDB/data/CO2 hydrogenation - General Data.csv
pyThermoDB/data/CO2 hydrogenation - The Molar Heat Capacities of Gases in the Ideal Gas (Zero-Pressure) State.csv
pyThermoDB/data/CO2 hydrogenation - Vapor Pressure.csv
pyThermoDB/data/__init__.py
pyThermoDB/data/ref.py
pyThermoDB/docs/__init__.py
pyThermoDB/docs/tableref.py
pyThermoDB/docs/thermo.py
pyThermoDB/handlers/__init__.py
pyThermoDB/handlers/errors.py
pyThermoDB/loader/__init__.py
pyThermoDB/loader/customref.py
pyThermoDB/manager/__init__.py
pyThermoDB/manager/main.py
pyThermoDB/manager/managedata.py
pyThermoDB/models/__init__.py
pyThermoDB/models/conditions.py
pyThermoDB/models/configs.py
pyThermoDB/models/eq.py
pyThermoDB/models/property.py
pyThermoDB/models/ref.py
pyThermoDB/models/references.py
pyThermoDB/models/rules.py
pyThermoDB/models/tables.py
pyThermoDB/references/__init__.py
pyThermoDB/references/builder.py
pyThermoDB/references/checker.py
pyThermoDB/references/config.py
pyThermoDB/references/content.py
pyThermoDB/references/databook.py
pyThermoDB/references/main.py
pyThermoDB/references/reference.py
pyThermoDB/references/reference_mapper.py
pyThermoDB/references/symbols_controller.py
pyThermoDB/references/table.py
pyThermoDB/transformer/__init__.py
pyThermoDB/transformer/transdata.py
pyThermoDB/transformer/transmatrixdata.py
pythermodb-1.12.2.dist-info/licenses/LICENSE
pythermodb-1.12.2.dist-info/METADATA
pythermodb-1.12.2.dist-info/WHEEL
pythermodb-1.12.2.dist-info/top_level.txt
pythermodb-1.12.2.dist-info/RECORD
