Metadata-Version: 2.4
Name: pyThermoDB
Version: 1.12.2
Summary: PyThermoDB is a lightweight and user-friendly Python package designed to provide quick access to essential thermodynamic data.
Home-page: https://github.com/sinagilassi/PyThermoDB
Author: Sina Gilassi
Author-email: Sina Gilassi <sina.gilassi@gmail.com>
License-Expression: MIT
Project-URL: Homepage, https://github.com/sinagilassi/PyThermoDB
Project-URL: Documentation, https://pythermodb.readthedocs.io/en/latest/
Project-URL: Source, https://github.com/sinagilassi/PyThermoDB
Project-URL: Tracker, https://github.com/sinagilassi/PyThermoDB/issues
Keywords: chemical-engineering,thermodynamics,thermodynamic-data,thermodynamic-equations,thermodynamic-properties
Classifier: Development Status :: 1 - Planning
Classifier: Intended Audience :: Education
Classifier: Programming Language :: Python :: 3.11
Classifier: Operating System :: Unix
Classifier: Operating System :: MacOS :: MacOS X
Classifier: Operating System :: Microsoft :: Windows
Requires-Python: >=3.10
License-File: LICENSE
Requires-Dist: numpy>=2.3.2
Requires-Dist: pandas>=2.3.2
Requires-Dist: pydantic>=2.11.7
Requires-Dist: pydantic-settings>=2.10.1
Requires-Dist: requests>=2.32.5
Requires-Dist: pyyaml>=6.0.3
Requires-Dist: pythermodb-settings>=0.2.1
Provides-Extra: dev
Requires-Dist: rich>=14.2.0; extra == "dev"
Dynamic: author
Dynamic: home-page
Dynamic: license-file
Dynamic: requires-python
